polygon_api_access/__init__.py
polygon_api_access/access.py
polygon_api_access-0.0.4.dist-info/METADATA
polygon_api_access-0.0.4.dist-info/WHEEL
polygon_api_access-0.0.4.dist-info/top_level.txt
polygon_api_access-0.0.4.dist-info/RECORD
