Metadata-Version: 2.1
Name: polygon-api-access
Version: 0.0.4
Summary: Polygon API Access
Home-page: https://polygon-api-access.readthedocs.io/
Author: Julius Dsouza
Author-email: jsdsz1996@gmail.com
License: MIT
Platform: UNKNOWN
Classifier: Intended Audience :: Developers
Classifier: License :: OSI Approved :: MIT License
Classifier: Programming Language :: Python
Classifier: Programming Language :: Python :: 3
Classifier: Programming Language :: Python :: 3.6
Classifier: Programming Language :: Python :: 3.7
Classifier: Programming Language :: Python :: 3.8
Classifier: Programming Language :: Python :: 3.9
Classifier: Operating System :: OS Independent
Requires-Dist: polygon-api-client
Requires-Dist: SQLAlchemy
Requires-Dist: python-dotenv
